setup.py
tf/__init__.py
tf/__main__.py
tf/environment.py
tflib.egg-info/PKG-INFO
tflib.egg-info/SOURCES.txt
tflib.egg-info/dependency_links.txt
tflib.egg-info/top_level.txt