Metadata-Version: 1.0
Name: tflib
Version: 0.1.0
Summary: Test Framework
Home-page: UNKNOWN
Author: Testing Required
Author-email: kyleetilley@gmail.com
License: UNKNOWN
Platform: UNKNOWN
